[
    {
        "model": "orders.order",
        "pk": 1,
        "fields": {
            "first_name": "Дмитрий",
            "last_name": "Тышкевич",
            "email": "tyshkevich.dima@mail.ru",
            "address": "ул. Ленина 12-2",
            "city": "Березинское",
            "created": "2023-06-18T16:04:42.033Z",
            "updated": "2023-06-18T16:04:42.033Z",
            "phone": "000-000-00000",
            "paid": false
        }
    },
    {
        "model": "orders.order",
        "pk": 2,
        "fields": {
            "first_name": "Дмитрий",
            "last_name": "Странковский",
            "email": "strankowski.dima@mail.ru",
            "address": "ул. Ленина 12-2",
            "city": "Березинское",
            "created": "2023-06-18T16:10:55.384Z",
            "updated": "2023-06-18T16:10:55.384Z",
            "phone": "000-000-00000",
            "paid": false
        }
    },
    {
        "model": "orders.order",
        "pk": 3,
        "fields": {
            "first_name": "Дмитрий",
            "last_name": "Тышкевич",
            "email": "tyshkevich.dima@mail.ru",
            "address": "ул. Ленина 12-2",
            "city": "Минск",
            "created": "2023-06-19T17:20:33.447Z",
            "updated": "2023-06-19T17:20:33.447Z",
            "phone": "+375 (33) 320",
            "paid": false
        }
    },
    {
        "model": "orders.order",
        "pk": 4,
        "fields": {
            "first_name": "Евгений",
            "last_name": "Сидоров",
            "email": "evgen@gmail.com",
            "address": "ул. Привокзальная 1",
            "city": "Березинское",
            "created": "2023-06-19T17:23:36.536Z",
            "updated": "2023-06-19T17:23:36.536Z",
            "phone": "+375333203255",
            "paid": false
        }
    },
    {
        "model": "orders.order",
        "pk": 5,
        "fields": {
            "first_name": "Дмитрий",
            "last_name": "Тышкевич",
            "email": "tyshkevich.dima@mail.ru",
            "address": "ул. Ленина 12-2",
            "city": "Минск",
            "created": "2023-06-22T06:03:43.334Z",
            "updated": "2023-06-22T06:03:43.334Z",
            "phone": "+375333204254",
            "paid": false
        }
    },
    {
        "model": "orders.order",
        "pk": 6,
        "fields": {
            "first_name": "Дмитрий",
            "last_name": "Тышкевич",
            "email": "tyshkevich.dima@mail.ru",
            "address": "ул. Ленина 12-2",
            "city": "Минск",
            "created": "2023-06-22T06:06:05.114Z",
            "updated": "2023-06-22T06:06:05.114Z",
            "phone": "+375333204254",
            "paid": false
        }
    },
    {
        "model": "orders.order",
        "pk": 7,
        "fields": {
            "first_name": "Дмитрий",
            "last_name": "Тышкевич",
            "email": "tyshkevich.dima@mail.ru",
            "address": "ул. Ленина 12-2",
            "city": "Минск",
            "created": "2023-06-22T06:36:12.476Z",
            "updated": "2023-06-22T06:36:12.476Z",
            "phone": "+375333204254",
            "paid": false
        }
    },
    {
        "model": "orders.order",
        "pk": 8,
        "fields": {
            "first_name": "Дмитрий",
            "last_name": "Тышкевич",
            "email": "tyshkevich.dima@mail.ru",
            "address": "ул. Ленина 12-2",
            "city": "Минск",
            "created": "2023-06-22T06:36:16.412Z",
            "updated": "2023-06-22T06:36:16.412Z",
            "phone": "+375333204254",
            "paid": false
        }
    },
    {
        "model": "orders.order",
        "pk": 9,
        "fields": {
            "first_name": "Дмитрий",
            "last_name": "Тышкевич",
            "email": "tyshkevich.dima@mail.ru",
            "address": "ул. Ленина 12-2",
            "city": "Минск",
            "created": "2023-06-22T06:36:31.935Z",
            "updated": "2023-06-22T06:36:31.935Z",
            "phone": "+375333204254",
            "paid": false
        }
    },
    {
        "model": "orders.order",
        "pk": 10,
        "fields": {
            "first_name": "Дмитрий",
            "last_name": "Тышкевич",
            "email": "tyshkevich.dima@mail.ru",
            "address": "ул. Ленина 12-2",
            "city": "Минск",
            "created": "2023-06-22T06:36:34.797Z",
            "updated": "2023-06-22T06:36:34.797Z",
            "phone": "+375333204254",
            "paid": false
        }
    },
    {
        "model": "orders.order",
        "pk": 11,
        "fields": {
            "first_name": "Дмитрий",
            "last_name": "Тышкевич",
            "email": "tyshkevich.dima@mail.ru",
            "address": "ул. Ленина 12-2",
            "city": "Минск",
            "created": "2023-06-22T06:37:03.231Z",
            "updated": "2023-06-22T06:37:03.231Z",
            "phone": "+375333204254",
            "paid": false
        }
    },
    {
        "model": "orders.order",
        "pk": 12,
        "fields": {
            "first_name": "Дмитрий",
            "last_name": "Странковский",
            "email": "tyshkevich.dima@mail.ru",
            "address": "ул. Ленина 12-2",
            "city": "Минск",
            "created": "2023-06-22T07:09:25.264Z",
            "updated": "2023-06-22T07:09:25.264Z",
            "phone": "+375333204254",
            "paid": false
        }
    },
    {
        "model": "orders.order",
        "pk": 13,
        "fields": {
            "first_name": "Дмитрий",
            "last_name": "Странковский",
            "email": "tyshkevich.dima@mail.ru",
            "address": "ул. Ленина 12-2",
            "city": "Минск",
            "created": "2023-06-22T07:09:48.163Z",
            "updated": "2023-06-22T07:09:48.163Z",
            "phone": "+375333204254",
            "paid": false
        }
    },
    {
        "model": "orders.order",
        "pk": 14,
        "fields": {
            "first_name": "Дмитрий",
            "last_name": "Странковский",
            "email": "tyshkevich.dima@mail.ru",
            "address": "ул. Ленина 12-2",
            "city": "Минск",
            "created": "2023-06-22T07:10:11.098Z",
            "updated": "2023-06-22T07:10:11.098Z",
            "phone": "+375333204254",
            "paid": false
        }
    },
    {
        "model": "orders.order",
        "pk": 15,
        "fields": {
            "first_name": "Дмитрий",
            "last_name": "Странковский",
            "email": "tyshkevich.dima@mail.ru",
            "address": "ул. Ленина 12-2",
            "city": "Минск",
            "created": "2023-06-22T07:10:19.040Z",
            "updated": "2023-06-22T07:10:19.040Z",
            "phone": "+375333204254",
            "paid": false
        }
    },
    {
        "model": "orders.order",
        "pk": 16,
        "fields": {
            "first_name": "Дмитрий",
            "last_name": "Тышкевич",
            "email": "tyshkevich.dima@mail.ru",
            "address": "ул. Ленина 12-2",
            "city": "Минск",
            "created": "2023-06-22T07:10:45.867Z",
            "updated": "2023-06-22T07:10:45.867Z",
            "phone": "+375333204254",
            "paid": false
        }
    },
    {
        "model": "orders.order",
        "pk": 17,
        "fields": {
            "first_name": "Дмитрий",
            "last_name": "Сидоров",
            "email": "strankowski.dima@mail.ru",
            "address": "ул. Ленина 12-2",
            "city": "Минск",
            "created": "2023-06-22T07:14:20.667Z",
            "updated": "2023-06-22T07:14:20.667Z",
            "phone": "+375333204254",
            "paid": false
        }
    },
    {
        "model": "orders.order",
        "pk": 18,
        "fields": {
            "first_name": "Степан",
            "last_name": "Сидоров",
            "email": "tyshkevich.dima@mail.ru",
            "address": "ул. Привокзальная 1",
            "city": "Березинское",
            "created": "2023-06-22T07:15:46.080Z",
            "updated": "2023-06-22T07:15:46.080Z",
            "phone": "+375333204254",
            "paid": false
        }
    },
    {
        "model": "orders.order",
        "pk": 19,
        "fields": {
            "first_name": "Степан",
            "last_name": "Сидоров",
            "email": "tyshkevich.dima@mail.ru",
            "address": "ул. Привокзальная 1",
            "city": "Березинское",
            "created": "2023-06-22T07:16:25.148Z",
            "updated": "2023-06-22T07:16:25.148Z",
            "phone": "+375333204254",
            "paid": false
        }
    },
    {
        "model": "orders.order",
        "pk": 20,
        "fields": {
            "first_name": "Дмитрий",
            "last_name": "Странковский",
            "email": "strankowski.dima@mail.ru",
            "address": "ул. Ленина 12-2",
            "city": "Минск",
            "created": "2023-06-22T07:28:01.840Z",
            "updated": "2023-06-22T07:28:01.840Z",
            "phone": "+375333204254",
            "paid": false
        }
    },
    {
        "model": "orders.order",
        "pk": 21,
        "fields": {
            "first_name": "Дмитрий",
            "last_name": "Сидоров",
            "email": "tyshkevich.dima@mail.ru",
            "address": "ул. Ленина 12-2",
            "city": "Минск",
            "created": "2023-06-22T07:35:32.945Z",
            "updated": "2023-06-22T07:35:32.945Z",
            "phone": "+375333204254",
            "paid": false
        }
    },
    {
        "model": "orders.order",
        "pk": 126,
        "fields": {
            "first_name": "Дмитрий",
            "last_name": "Тышкевич",
            "email": "tyshkevich.dima@mail.ru",
            "address": "ул. Ленина 12-2",
            "city": "Минск",
            "created": "2023-07-18T14:12:53.944Z",
            "updated": "2023-07-18T14:12:53.945Z",
            "phone": "+375333204254",
            "paid": false
        }
    },
    {
        "model": "orders.order",
        "pk": 127,
        "fields": {
            "first_name": "Дмитрий",
            "last_name": "Тышкевич",
            "email": "tyshkevich.dima@mail.ru",
            "address": "ул. Ленина 12-2",
            "city": "Минск",
            "created": "2023-07-18T15:17:09.444Z",
            "updated": "2023-07-18T15:17:09.444Z",
            "phone": "+375333204254",
            "paid": false
        }
    },
    {
        "model": "orders.order",
        "pk": 128,
        "fields": {
            "first_name": "Дмитрий",
            "last_name": "Тышкевич",
            "email": "tyshkevich.dima@mail.ru",
            "address": "ул. Ленина 12-2",
            "city": "Минск",
            "created": "2023-07-20T08:54:53.366Z",
            "updated": "2023-07-20T08:54:53.367Z",
            "phone": "+375333204254",
            "paid": false
        }
    },
    {
        "model": "orders.order",
        "pk": 129,
        "fields": {
            "first_name": "Дмитрий",
            "last_name": "Тышкевич",
            "email": "tyshkevich.dima@mail.ru",
            "address": "ул. Ленина 12-2",
            "city": "Минск",
            "created": "2023-07-20T11:48:07.328Z",
            "updated": "2023-07-20T11:48:07.328Z",
            "phone": "+375333204254",
            "paid": false
        }
    },
    {
        "model": "orders.order",
        "pk": 130,
        "fields": {
            "first_name": "Дмитрий",
            "last_name": "Тышкевич",
            "email": "tyshkevich.dima@mail.ru",
            "address": "ул. Ленина 12-2",
            "city": "Минск",
            "created": "2023-07-20T11:52:38.396Z",
            "updated": "2023-07-20T11:52:38.396Z",
            "phone": "+375333204254",
            "paid": false
        }
    },
    {
        "model": "orders.order",
        "pk": 131,
        "fields": {
            "first_name": "Дмитрий",
            "last_name": "Тышкевич",
            "email": "tihon2008199213@gmail.com",
            "address": "ул. Ленина 12-2",
            "city": "Минск",
            "created": "2023-07-20T11:56:48.914Z",
            "updated": "2023-07-20T11:56:48.914Z",
            "phone": "+375333204254",
            "paid": false
        }
    },
    {
        "model": "orders.order",
        "pk": 132,
        "fields": {
            "first_name": "Дмитрий",
            "last_name": "Тышкевич",
            "email": "tyshkevich.dima@mail.ru",
            "address": "ул. Ленина 12-2",
            "city": "Минск",
            "created": "2023-07-20T12:01:31.050Z",
            "updated": "2023-07-20T12:01:31.050Z",
            "phone": "+375333204254",
            "paid": false
        }
    },
    {
        "model": "orders.order",
        "pk": 159,
        "fields": {
            "first_name": "Дмитрий",
            "last_name": "Тышкевич",
            "email": "tyshkevich.dima@mail.ru",
            "address": "ул. Ленина 12-2",
            "city": "Минск",
            "created": "2023-08-02T10:26:22.366Z",
            "updated": "2023-08-02T10:26:22.366Z",
            "phone": "+375 33 320-42-54",
            "paid": false
        }
    },
    {
        "model": "orders.order",
        "pk": 160,
        "fields": {
            "first_name": "Дмитрий",
            "last_name": "Тышкевич",
            "email": "tyshkevich.dima@mail.ru",
            "address": "ул. Ленина 12-2",
            "city": "Минск",
            "created": "2023-08-23T06:24:49.154Z",
            "updated": "2023-08-23T06:24:49.154Z",
            "phone": "+375 33 320-42-54",
            "paid": false
        }
    },
    {
        "model": "orders.order",
        "pk": 161,
        "fields": {
            "first_name": "Дмитрий",
            "last_name": "Тышкевич",
            "email": "tyshkevich.dima@mail.ru",
            "address": "ул. Ленина 12-2",
            "city": "Минск",
            "created": "2023-08-23T07:33:20.374Z",
            "updated": "2023-08-23T07:33:20.374Z",
            "phone": "+375 33 320-42-54",
            "paid": false
        }
    },
    {
        "model": "orders.order",
        "pk": 162,
        "fields": {
            "first_name": "Дмитрий",
            "last_name": "Тышкевич",
            "email": "tyshkevich.dima@mail.ru",
            "address": "ул. Ленина 12-2",
            "city": "Минск",
            "created": "2023-08-23T07:36:36.630Z",
            "updated": "2023-08-23T07:36:36.630Z",
            "phone": "+375 33 320-42-54",
            "paid": false
        }
    },
    {
        "model": "orders.order",
        "pk": 163,
        "fields": {
            "first_name": "Дмитрий",
            "last_name": "Тышкевич",
            "email": "tyshkevich.dima@mail.ru",
            "address": "ул. Ленина 12-2",
            "city": "Минск",
            "created": "2023-08-23T07:41:05.077Z",
            "updated": "2023-08-23T07:41:05.077Z",
            "phone": "+375 33 320-42-54",
            "paid": false
        }
    },
    {
        "model": "orders.order",
        "pk": 164,
        "fields": {
            "first_name": "Дмитрий",
            "last_name": "Тышкевич",
            "email": "tyshkevich.dima@mail.ru",
            "address": "ул. Ленина 12-2",
            "city": "Минск",
            "created": "2023-08-23T10:35:16.344Z",
            "updated": "2023-08-23T10:35:16.344Z",
            "phone": "+375 33 320-42-54",
            "paid": false
        }
    },
    {
        "model": "orders.order",
        "pk": 165,
        "fields": {
            "first_name": "Дмитрий",
            "last_name": "Тышкевич",
            "email": "tyshkevich.dima@mail.ru",
            "address": "ул. Привокзальная 1",
            "city": "Березинское",
            "created": "2023-08-25T10:56:23.516Z",
            "updated": "2023-08-25T10:56:23.516Z",
            "phone": "+375 33 320-42-54",
            "paid": false
        }
    },
    {
        "model": "orders.order",
        "pk": 166,
        "fields": {
            "first_name": "Дмитрий",
            "last_name": "Тышкевич",
            "email": "tyshkevich.dima@mail.ru",
            "address": "ул. Привокзальная 1",
            "city": "Березинское",
            "created": "2023-08-28T15:26:21.246Z",
            "updated": "2023-08-28T15:26:21.246Z",
            "phone": "+375 33 320-42-54",
            "paid": false
        }
    },
    {
        "model": "orders.order",
        "pk": 167,
        "fields": {
            "first_name": "Дмитрий",
            "last_name": "Волосевич",
            "email": "tyshkevich.dima@mail.ru",
            "address": "ул. Привокзальная 1",
            "city": "Березинское",
            "created": "2023-08-28T15:29:32.373Z",
            "updated": "2023-08-28T15:29:32.373Z",
            "phone": "+375 33 320-42-54",
            "paid": false
        }
    },
    {
        "model": "orders.order",
        "pk": 168,
        "fields": {
            "first_name": "Дмитрий",
            "last_name": "Волосевич",
            "email": "tyshkevich.dima@mail.ru",
            "address": "ул. Привокзальная 1",
            "city": "Березинское",
            "created": "2023-08-28T15:29:36.578Z",
            "updated": "2023-08-28T15:29:36.578Z",
            "phone": "+375 33 320-42-54",
            "paid": false
        }
    },
    {
        "model": "orders.order",
        "pk": 169,
        "fields": {
            "first_name": "Дмитрий",
            "last_name": "Тышкевич",
            "email": "tyshkevich.dima@mail.ru",
            "address": "ул. Привокзальная 1",
            "city": "Березинское",
            "created": "2023-09-11T14:56:09.332Z",
            "updated": "2023-09-11T14:56:09.332Z",
            "phone": "+375 33 320-42-54",
            "paid": false
        }
    },
    {
        "model": "orders.order",
        "pk": 170,
        "fields": {
            "first_name": "Дмитрий",
            "last_name": "Тышкевич",
            "email": "tyshkevich.dima@mail.ru",
            "address": "ул. Привокзальная 1",
            "city": "Минск",
            "created": "2023-09-11T15:05:23.074Z",
            "updated": "2023-09-11T15:05:23.074Z",
            "phone": "+375 33 320-42-54",
            "paid": false
        }
    }
]